MANIFEST.in
NEWS.txt
README.txt
requirements.txt
setup.cfg
setup.py
src/tacot/__init__.py
src/tacot/docopt.py
src/tacot/manifest.py
src/tacot.egg-info/PKG-INFO
src/tacot.egg-info/SOURCES.txt
src/tacot.egg-info/dependency_links.txt
src/tacot.egg-info/entry_points.txt
src/tacot.egg-info/not-zip-safe
src/tacot.egg-info/top_level.txt