Metadata-Version: 1.1
Name: tacot
Version: 0.3.5
Summary: With Tacot generate easily your statics web sites
Home-page: http://packages.python.org/tacot/
Author: Stephane Klein
Author-email: contact@stephane-klein.info
License: MIT License
Keywords: static generator web
Platform: UNKNOWN
Classifier: Development Status :: 5 - Production/Stable
Classifier: Environment :: Console
Classifier: Operating System :: OS Independent
Classifier: Programming Language :: Python :: 2.7
Classifier: Programming Language :: Python :: 2.6
Classifier: Topic :: Internet :: WWW/HTTP
